[
  {
    "id": "news_215973281751",
    "source": "gdelt",
    "title": "Conagra Brands Slashes Its 10 % Dividend Yield in Half Just 1 Month After Getting Kicked Out of the S & P 500 . Here Why the Stock Isnt Tanking . ",
    "url": "https://www.fool.com/investing/2026/07/19/conagra-slashes-its-10-dividend-yield-in-half-just/?source=iedfolrf0000001",
    "published_at": "2026-07-19T11:30:00+00:00",
    "language": "English",
    "domain": "fool.com",
    "country": "United States",
    "tickers_detected": [
      "CAG"
    ],
    "themes": [
      "stock"
    ],
    "event_date": "2026-07-19",
    "known_date": "2026-07-19",
    "scrape_date": "2026-07-21T23:22:06+00:00",
    "delay_days": 0
  },
  {
    "id": "news_803260389854",
    "source": "gdelt",
    "title": "SteelPeak Wealth LLC Makes New Investment in Conagra Brands $CAG",
    "url": "https://www.themarketsdaily.com/2026/07/19/steelpeak-wealth-llc-makes-new-investment-in-conagra-brands-cag.html",
    "published_at": "2026-07-19T09:30:00+00:00",
    "language": "English",
    "domain": "themarketsdaily.com",
    "country": "United States",
    "tickers_detected": [
      "CAG"
    ],
    "themes": [],
    "event_date": "2026-07-19",
    "known_date": "2026-07-19",
    "scrape_date": "2026-07-21T23:22:06+00:00",
    "delay_days": 0
  },
  {
    "id": "news_165031990545",
    "source": "gdelt",
    "title": "Conagra Brands Slashes Its 10 % Dividend Yield in Half Just 1 Month After Getting Kicked Out of the S & P 500 . Here Why the Stock Isnt Tanking . ",
    "url": "https://www.fool.com/investing/2026/07/19/conagra-slashes-its-10-dividend-yield-in-half-just/",
    "published_at": "2026-07-19T08:30:00+00:00",
    "language": "English",
    "domain": "fool.com",
    "country": "United States",
    "tickers_detected": [
      "CAG"
    ],
    "themes": [
      "stock"
    ],
    "event_date": "2026-07-19",
    "known_date": "2026-07-19",
    "scrape_date": "2026-07-21T23:22:06+00:00",
    "delay_days": 0
  },
  {
    "id": "news_699332663351",
    "source": "gdelt",
    "title": "Northfield Bancorp ( NASDAQ : NFBK ) Sets New 1 - Year High – Should You Buy ? ",
    "url": "https://www.themarketsdaily.com/2026/07/17/northfield-bancorp-nasdaqnfbk-sets-new-1-year-high-should-you-buy.html",
    "published_at": "2026-07-17T16:45:00+00:00",
    "language": "English",
    "domain": "themarketsdaily.com",
    "country": "United States",
    "tickers_detected": [
      "NFBK"
    ],
    "themes": [
      "regulatory"
    ],
    "event_date": "2026-07-17",
    "known_date": "2026-07-17",
    "scrape_date": "2026-07-21T23:20:54+00:00",
    "delay_days": 0
  },
  {
    "id": "news_273801736614",
    "source": "gdelt",
    "title": "Maplight Therapeutics ( NASDAQ : MPLT ) Sets New 1 - Year High – Time to Buy ? ",
    "url": "https://www.dailypolitical.com/2026/07/10/maplight-therapeutics-nasdaqmplt-sets-new-1-year-high-time-to-buy.html",
    "published_at": "2026-07-10T19:15:00+00:00",
    "language": "English",
    "domain": "dailypolitical.com",
    "country": "United States",
    "tickers_detected": [
      "MPLT"
    ],
    "themes": [],
    "event_date": "2026-07-10",
    "known_date": "2026-07-10",
    "scrape_date": "2026-07-21T23:23:55+00:00",
    "delay_days": 0
  },
  {
    "id": "news_238685952562",
    "source": "gdelt",
    "title": "Research Analyst Recent Ratings Changes for Maplight Therapeutics ( MPLT ) ",
    "url": "https://www.dailypolitical.com/2026/07/09/research-analysts-recent-ratings-changes-for-maplight-therapeutics-mplt.html",
    "published_at": "2026-07-09T18:15:00+00:00",
    "language": "English",
    "domain": "dailypolitical.com",
    "country": "United States",
    "tickers_detected": [
      "MPLT"
    ],
    "themes": [],
    "event_date": "2026-07-09",
    "known_date": "2026-07-09",
    "scrape_date": "2026-07-21T23:23:55+00:00",
    "delay_days": 0
  }
]