[
  {
    "id": "news_219336369524",
    "source": "gdelt",
    "title": "Pinterest Creator Fund Incentivizes Use Of  Inclusive  Search Features",
    "url": "https://www.mediapost.com/publications/article/416735/pinterest-creator-fund-incentivizes-use-of-inclus.html",
    "published_at": "2026-07-22T20:30:00+00:00",
    "language": "English",
    "domain": "mediapost.com",
    "country": "United States",
    "tickers_detected": [
      "PINS"
    ],
    "themes": [],
    "event_date": "2026-07-22",
    "known_date": "2026-07-22",
    "scrape_date": "2026-07-22T22:29:05+00:00",
    "delay_days": 0
  },
  {
    "id": "news_435660672486",
    "source": "gdelt",
    "title": "Freenome Debuts as a Publicly Traded Company Focused on Blood - Based Early Cancer Detection",
    "url": "https://www.manilatimes.net/2026/07/21/tmt-newswire/globenewswire/freenome-debuts-as-a-publicly-traded-company-focused-on-blood-based-early-cancer-detection/2387946",
    "published_at": "2026-07-20T21:00:00+00:00",
    "language": "English",
    "domain": "manilatimes.net",
    "country": "Philippines",
    "tickers_detected": [
      "FRNM"
    ],
    "themes": [],
    "event_date": "2026-07-20",
    "known_date": "2026-07-20",
    "scrape_date": "2026-07-22T22:26:19+00:00",
    "delay_days": 0
  },
  {
    "id": "news_125754649126",
    "source": "gdelt",
    "title": "Freenome colorectal cancer test data improve on earlier results",
    "url": "https://www.biopharmadive.com/news/freenome-colorectal-cancer-test-data-improve-on-earlier-results/825085/",
    "published_at": "2026-07-14T17:30:00+00:00",
    "language": "English",
    "domain": "biopharmadive.com",
    "country": "United States",
    "tickers_detected": [
      "FRNM"
    ],
    "themes": [],
    "event_date": "2026-07-14",
    "known_date": "2026-07-14",
    "scrape_date": "2026-07-22T22:26:19+00:00",
    "delay_days": 0
  },
  {
    "id": "news_628576457931",
    "source": "gdelt",
    "title": "Here Why TON Strategy ( TONX ) is Among the 10 Fastest Growing Tech Penny Stocks to Buy",
    "url": "https://finance.yahoo.com/markets/stocks/articles/why-ton-strategy-tonx-among-103341074.html",
    "published_at": "2026-07-14T11:15:00+00:00",
    "language": "English",
    "domain": "finance.yahoo.com",
    "country": "United States",
    "tickers_detected": [
      "TONX"
    ],
    "themes": [
      "stock"
    ],
    "event_date": "2026-07-14",
    "known_date": "2026-07-14",
    "scrape_date": "2026-07-22T22:26:38+00:00",
    "delay_days": 0
  }
]