{
  "generated_at": "2026-07-23T17:03:42+00:00",
  "portfolio": {
    "SPY": 0.1201,
    "QQQ": 0.0976,
    "TLT": 0.0976,
    "GLD": 0.0731,
    "BEP": 0.0582,
    "IEF": 0.0488,
    "CLBK": 0.048,
    "NMM": 0.0431,
    "LLY": 0.0411,
    "CAG": 0.0325,
    "TSM": 0.0222,
    "QNT": 0.011,
    "BFLY": 0.0065
  },
  "metrics": {
    "ann_vol": 0.0907,
    "var_95_1d": 0.0085,
    "cvar_95_1d": 0.0119,
    "max_drawdown": -0.0175,
    "beta_spy": 0.501,
    "hhi": 0.0522,
    "max_position": 0.1201,
    "n_positions": 13,
    "effective_positions": 19.2,
    "gross_exposure": 0.6998,
    "days_used": 33
  },
  "limits": {
    "max_position": 0.15,
    "max_sector": 0.4,
    "max_ann_vol": 0.25,
    "max_gross_exposure": 1.0,
    "respect_regime_budget": true
  },
  "regime_budget": 0.7,
  "gate": {
    "passed": true,
    "violations": [],
    "n_violations": 0
  },
  "monte_carlo": {
    "horizon_days": 21,
    "n_sims": 5000,
    "method": "historical_bootstrap",
    "expected_return_pct": -0.38,
    "median_return_pct": -0.41,
    "p5_return_pct": -4.55,
    "p25_return_pct": -2.14,
    "p75_return_pct": 1.32,
    "p95_return_pct": 3.91,
    "prob_loss": 0.562,
    "var_95_horizon": 0.0455,
    "cvar_95_horizon": 0.0554
  }
}